crescent/__init__.py
crescent/_about.py
crescent/banner.txt
crescent/client.py
crescent/commands/__init__.py
crescent/commands/decorators.py
crescent/commands/groups.py
crescent/commands/options.py
crescent/context/__init__.py
crescent/context/autocomplete_context.py
crescent/context/context.py
crescent/context/interaction_context.py
crescent/errors.py
crescent/events.py
crescent/exceptions.py
crescent/ext/cooldowns/__init__.py
crescent/ext/cooldowns/py.typed
crescent/ext/locales/__init__.py
crescent/ext/tasks/__init__.py
crescent/ext/tasks/cron.py
crescent/ext/tasks/loop.py
crescent/ext/tasks/py.typed
crescent/ext/tasks/task.py
crescent/hooks.py
crescent/internal/__init__.py
crescent/internal/app_command.py
crescent/internal/handle_resp.py
crescent/internal/includable.py
crescent/internal/registry.py
crescent/locale.py
crescent/mentionable.py
crescent/plugin.py
crescent/py.typed
crescent/typedefs.py
crescent/utils/__init__.py
crescent/utils/any_issubclass.py
crescent/utils/gather_iter.py
crescent/utils/hooks.py
crescent/utils/options.py
crescent/utils/tasks.py
hikari_crescent-1.4.0.dist-info/METADATA
hikari_crescent-1.4.0.dist-info/WHEEL
hikari_crescent-1.4.0.dist-info/licenses/LICENSE
hikari_crescent-1.4.0.dist-info/RECORD
