Metadata-Version: 2.4
Name: hikari-crescent
Version: 1.4.0
Summary: 🌙 A command handler for Hikari that keeps your project neat and tidy.
License: MPL-2.0
License-File: LICENSE
Keywords: discord,hikari,command handler,slash commands,application commands
Author: Lunarmagpie
Author-email: bambolambo0@gmail.com
Maintainer: Lunarmagpie
Maintainer-email: bambolambo0@gmail.com
Requires-Python: >=3.10,<3.15
Classifier: Development Status :: 5 - Production/Stable
Classifier: License :: OSI Approved
Classifier: Programming Language :: Python :: 3
Classifier: Programming Language :: Python :: 3.10
Classifier: Programming Language :: Python :: 3.11
Classifier: Programming Language :: Python :: 3.12
Classifier: Programming Language :: Python :: 3.13
Classifier: Programming Language :: Python :: 3.14
Provides-Extra: cooldowns
Provides-Extra: cron
Provides-Extra: i18n
Requires-Dist: croniter (>=5.0.0,<6.0.0) ; extra == "cron"
Requires-Dist: floodgate-rs (>=0.1.1,<0.2.0) ; extra == "cooldowns"
Requires-Dist: hikari (>=2.3.0,<3.0.0)
Requires-Dist: python-i18n (>=0.2) ; extra == "i18n"
Requires-Dist: sigparse (>=3.0.0,<4.0.0)
Requires-Dist: types-croniter (>=5.0.0,<6.0.0) ; extra == "cron"
Project-URL: Documentation, https://hikari-crescent.github.io/hikari-crescent/crescent.html
Project-URL: Homepage, https://github.com/hikari-crescent/hikari-crescent
Project-URL: Repository, https://github.com/hikari-crescent/hikari-crescent
